adunblock_server_tag_django-1.0.0.dist-info/licenses/LICENSE
server_tag/__init__.py
server_tag/apps.py
server_tag/templatetags/__init__.py
server_tag/templatetags/server_tag_tags.py
adunblock_server_tag_django-1.0.0.dist-info/METADATA
adunblock_server_tag_django-1.0.0.dist-info/WHEEL
adunblock_server_tag_django-1.0.0.dist-info/top_level.txt
adunblock_server_tag_django-1.0.0.dist-info/RECORD
