Metadata-Version: 2.4
Name: adunblock-server-tag-django
Version: 1.0.0
Summary: A Django package to fetch and render scripts from a remote URL with template tag integration and caching support.
Author-email: Adunblock <dev@adunblock.com>
License: ISC
Project-URL: Homepage, https://github.com/adunblock/adunblock-server-tag
Project-URL: Repository, https://github.com/adunblock/adunblock-server-tag
Project-URL: Issues, https://github.com/adunblock/adunblock-server-tag/issues
Keywords: django,python,server-tag,script-loading,remote-scripts,template-tags
Classifier: Development Status :: 5 - Production/Stable
Classifier: Environment :: Web Environment
Classifier: Framework :: Django
Classifier: Framework :: Django :: 3.2
Classifier: Framework :: Django :: 4.0
Classifier: Framework :: Django :: 4.1
Classifier: Framework :: Django :: 4.2
Classifier: Framework :: Django :: 5.0
Classifier: Intended Audience :: Developers
Classifier: License :: OSI Approved :: ISC License (ISCL)
Classifier: Operating System :: OS Independent
Classifier: Programming Language :: Python
Classifier: Programming Language :: Python :: 3
Classifier: Programming Language :: Python :: 3.8
Classifier: Programming Language :: Python :: 3.9
Classifier: Programming Language :: Python :: 3.10
Classifier: Programming Language :: Python :: 3.11
Classifier: Programming Language :: Python :: 3.12
Classifier: Topic :: Internet :: WWW/HTTP
Classifier: Topic :: Software Development :: Libraries :: Python Modules
Requires-Python: >=3.8
License-File: LICENSE
Requires-Dist: Django>=3.2
Requires-Dist: requests>=2.25.0
Dynamic: license-file
